reddit_downloader/__init__.py
reddit_downloader/main.py
reddit_downloader-0.0.2.dist-info/LICENSE
reddit_downloader-0.0.2.dist-info/METADATA
reddit_downloader-0.0.2.dist-info/WHEEL
reddit_downloader-0.0.2.dist-info/top_level.txt
reddit_downloader-0.0.2.dist-info/RECORD
