Metadata-Version: 2.1
Name: reddit-downloader
Version: 0.0.2
Summary: Image downloader based on subreddit.
Home-page: https://gitlab.com/jeffmc/reddit_image_downloader
Author: Jeffrey McAthey
Author-email: jeffmcathey@gmail.com
License: UNKNOWN
Platform: UNKNOWN
